pytimer2/__init__.py
pytimer2/timer.py
pytimer2-0.2.4.dist-info/LICENSE
pytimer2-0.2.4.dist-info/METADATA
pytimer2-0.2.4.dist-info/WHEEL
pytimer2-0.2.4.dist-info/top_level.txt
pytimer2-0.2.4.dist-info/RECORD
