Metadata-Version: 2.1
Name: pytimer2
Version: 0.2.4
Summary: PyTimer is a lightweight and easy-to-use Python package designed to provide countdown timer functionality. It offers a simple class-based approach to manage countdowns, making it perfect for various use cases such as timing events, tracking intervals, or managing delays in scripts and applications.
Home-page: https://github.com/attiqRahman/pytimer
Author: Atiqur Rahman
Author-email: rahman.md.attiq@gmail.com
License: UNKNOWN
Platform: UNKNOWN
Classifier: Programming Language :: Python :: 3
Classifier: License :: OSI Approved :: MIT License
Classifier: Operating System :: OS Independent
Requires-Python: >=3.6
License-File: LICENSE
